[{"id":"asfaswaf","q":"What does fish taste like?","u":"Anon","a":[{"u":"Anon","a":"salmon"},{"u":"Mike","a":"Toast"}]},{"id":"grwasdea","q":"What does fish taste like?","u":"Anon","a":[{"u":"Anon","a":"Fish tastes like salmonella"},{"u":"Anon","a":"PHIS POSH"}]},{"id":"fsawfrsa","q":"Are caars human?","u":"Anon","a":[{"u":"Kim","a":"no"},{"u":"Joseph","a":"Yes, ofc. who told you otherwise?"}]},{"id":"982fNEkM","q":"What is the difference between a black spotted lizard, and a normal lizard?","u":"","a":[]}]